blip/__init__.py
blip/constants.py
blip/custom_test_runner.py
blip/service.py
django_blip-0.0.10.dist-info/LICENSE
django_blip-0.0.10.dist-info/METADATA
django_blip-0.0.10.dist-info/WHEEL
django_blip-0.0.10.dist-info/top_level.txt
django_blip-0.0.10.dist-info/RECORD
